<VG_SETUP format="vg">
  <XML_Version>3.2</XML_Version>
  <Description>
    <LongDesc>Greenhouse 10.000 m2 with HeatPumps</LongDesc>
    <WeatherFile>DNK_Odense.txt</WeatherFile>
    <Country>Finland</Country>
    <Location>Tempera                                           </Location>
    <Longitude>23.761</Longitude>
    <Latitude>61.4978</Latitude>
    <StartTime>01-01-2024</StartTime>
    <StopTime>03-01-2024</StopTime>
    <TimeStep>3</TimeStep>
    <ShortDesc>HeatPump</ShortDesc>
  </Description>
  <Greenhouse>
    <Positions>
      <roof1 position="1">
        <Weight>1</Weight>
      </roof1>
      <roof2 position="2">
        <Weight>1</Weight>
      </roof2>
      <side1 position="3">
        <Weight>0.6</Weight>
      </side1>
      <side2 position="4">
        <Weight>0.6</Weight>
      </side2>
      <end1 position="5">
        <Weight>0.2</Weight>
      </end1>
      <end2 position="6">
        <Weight>0.2</Weight>
      </end2>
    </Positions>
    <Length>100</Length>
    <SpanSize>4</SpanSize>
    <NumberOfSpans>25</NumberOfSpans>
    <GreenhouseReductionFactorLight>0.2</GreenhouseReductionFactorLight>
    <TrempelHeight>4</TrempelHeight>
    <RoofPitch>26</RoofPitch>
    <UwindSlope>0.5</UwindSlope>
    <leakage>0.1</leakage>
    <screenPerfection>0.95</screenPerfection>
    <floor-Uindoors>7.5</floor-Uindoors>
    <floor-Usoil>0.1</floor-Usoil>
    <floor-heatCapacity>42000</floor-heatCapacity>
    <floor-reflectance>0.4</floor-reflectance>
    <HasHeatSink>0</HasHeatSink>
    <priceHeat>30</priceHeat>
    <pricePower>60</pricePower>
    <Currency>missing</Currency>
    <CalibrationHeat>1</CalibrationHeat>
    <CalibrationPower>1</CalibrationPower>
    <InitialSoilTemperature>1.7</InitialSoilTemperature>
    <CO2PIDProp>0.05</CO2PIDProp>
    <ScreenLagPeriod>10</ScreenLagPeriod>
    <VentWindCoef>50</VentWindCoef>
    <VentTemperatureCoef>14</VentTemperatureCoef>
    <HeatingPIDProp>0.05</HeatingPIDProp>
    <HeatPumpPIDProp>-0.05</HeatPumpPIDProp>
    <VentilationPIDProp>-0.0001</VentilationPIDProp>
    <TavgPIDProp>1.5</TavgPIDProp>
    <TavgPIDInt>0</TavgPIDInt>
    <TavgPIDDeriv>0.001</TavgPIDDeriv>
    <Crops>
      <Crop index="0" layer="0" position="0">
        <LAI>2.5</LAI>
        <Jmax25>145.5200</Jmax25>
        <GammaStar>53.2100</GammaStar>
        <lightRespiration>0.6800</lightRespiration>
        <BallBerryIntercept>0.0943</BallBerryIntercept>
        <BallBerrySlope>1.6400</BallBerrySlope>
        <propAreaCultured>0.95</propAreaCultured>
        <Product>PotRose</Product>
        <Vcmax25>88.1200</Vcmax25>
        <k>0.7</k>
        <re>200</re>
        <Km>600</Km>
        <alpha>0.8991</alpha>
        <theta>0.85</theta>
        <Q10>1.03</Q10>
        <Jmax>133.1700</Jmax>
      </Crop>
    </Crops>
    <Fogs>
      <Products>
        <Product name="None"> <!--NH-->
          <MaxHumidification>100</MaxHumidification>
          <Efficiency>0</Efficiency>
          <MaxParasitLoad>0</MaxParasitLoad>
        </Product>
      </Products>
      <Fog index="1" layer="1" position="1">
        <Product>None</Product>
        <Number>0</Number>
      </Fog>
      <Fog index="1" layer="1" position="2">
        <Product>None</Product>
        <Number>0</Number>
      </Fog>
      <Fog index="1" layer="1" position="3">
        <Product>None</Product>
        <Number>0</Number>
      </Fog>
      <Fog index="1" layer="1" position="4">
        <Product>None</Product>
        <Number>0</Number>
      </Fog>
      <Fog index="1" layer="1" position="5">
        <Product>None</Product>
        <Number>0</Number>
      </Fog>
      <Fog index="1" layer="1" position="6">
        <Product>None</Product>
        <Number>0</Number>
      </Fog>
      <Fog index="1" layer="1" position="7">
        <Product>None</Product>
        <Number>0</Number>
      </Fog>
      <Fog index="1" layer="1" position="8">
        <Product>None</Product>
        <Number>0</Number>
      </Fog>
    </Fogs>
    <HeatBuffer>
      <HeatBuffer index="1" layer="1" position="1">
        <Volume>25</Volume>
        <MaxTemperature>95</MaxTemperature>
        <U>10</U>
        <UptakeEfficiency>0.85</UptakeEfficiency>
        <ExtractionEfficiency>0.85</ExtractionEfficiency>
      </HeatBuffer>
    </HeatBuffer>
    <HeatExchangers>
      <Products>
        <Product Name="0.85">
          <MaxFlowRate>missing</MaxFlowRate>
          <MaxLoad>missing</MaxLoad>
          <Efficiency>missing</Efficiency>
          <MaxParasitLoad>missing</MaxParasitLoad>
          <HeatRecovery>missing</HeatRecovery>
        </Product>
      </Products>
      <HeatExchanger index="1" layer="1" position="1">
        <Product>0.85</Product>
        <Number>0</Number>
      </HeatExchanger>
      <HeatExchanger index="1" layer="1" position="2">
        <Product>0.85</Product>
        <Number>0</Number>
      </HeatExchanger>
      <HeatExchanger index="1" layer="1" position="3">
        <Product>0.85</Product>
        <Number>0</Number>
      </HeatExchanger>
      <HeatExchanger index="1" layer="1" position="4">
        <Product>0.85</Product>
        <Number>0</Number>
      </HeatExchanger>
      <HeatExchanger index="1" layer="1" position="5">
        <Product>0.85</Product>
        <Number>0</Number>
      </HeatExchanger>
      <HeatExchanger index="1" layer="1" position="6">
        <Product>0.85</Product>
        <Number>0</Number>
      </HeatExchanger>
      <HeatExchanger index="1" layer="1" position="7">
        <Product>0.85</Product>
        <Number>0</Number>
      </HeatExchanger>
      <HeatExchanger index="1" layer="1" position="8">
        <Product>0.85</Product>
        <Number>0</Number>
      </HeatExchanger>
    </HeatExchangers>
    <Heatpipes>
      <Heatpipe index="0" layer="0" position="1">
        <Product>41 mm Steel</Product>
        <PipeMaterialDesc>Iron</PipeMaterialDesc>
        <InnerDiameter>0.0390</InnerDiameter>
        <CommonFlowTemperature>80</CommonFlowTemperature>
        <heatPipeFlowRate>50</heatPipeFlowRate>
        <PipeLengthPerSqm>1.6</PipeLengthPerSqm>
        <k>0.0100</k>
        <b>1.5000</b>
        <PropLw>0.2000</PropLw>
      </Heatpipe>
      <Heatpipe index="0" layer="0" position="2">
        <Product>41 mm Steel</Product>
        <PipeMaterialDesc>Iron</PipeMaterialDesc>
        <InnerDiameter>0.0390</InnerDiameter>n
        <CommonFlowTemperature>80</CommonFlowTemperature>
        <heatPipeFlowRate>50</heatPipeFlowRate>
        <PipeLengthPerSqm>1.6</PipeLengthPerSqm>
        <k>0.0100</k>
        <b>1.5000</b>
        <PropLw>0.2000</PropLw>
      </Heatpipe>
    </Heatpipes>
    <HeatPumps>
      <Products>
        <Product name="Heat pump test 1">  <!--NH-->
          <MaxFlowRate>2.5</MaxFlowRate>
          <MaxCoolingLoad>78.4</MaxCoolingLoad>
          <CoolingEfficiency>0.69</CoolingEfficiency>
          <MaxParasitLoad>2.2</MaxParasitLoad>
          <CoolingTemperature>10</CoolingTemperature>
          <HeatRecovery>1</HeatRecovery>
        </Product>
        <Product name="None">  <!--NH-->
          <MaxFlowRate>0</MaxFlowRate>
          <MaxCoolingLoad>0</MaxCoolingLoad>
          <CoolingEfficiency>0</CoolingEfficiency>
          <MaxParasitLoad>0</MaxParasitLoad>
          <CoolingTemperature>0</CoolingTemperature>
          <HeatRecovery>0</HeatRecovery>
        </Product>
      </Products>
      <HeatPump index="1" layer="1" position="1">
        <Product>Heat pump test 1</Product>
        <Number>10</Number>
      </HeatPump>
      <HeatPump index="1" layer="1" position="2">
        <Product>None</Product>
        <Number>0</Number>
      </HeatPump>
      <HeatPump index="1" layer="1" position="3">
        <Product>None</Product>
        <Number>0</Number>
      </HeatPump>
      <HeatPump index="1" layer="1" position="4">
        <Product>None</Product>
        <Number>0</Number>
      </HeatPump>
      <HeatPump index="1" layer="1" position="5">
        <Product>None</Product>
        <Number>0</Number>
      </HeatPump>
      <HeatPump index="1" layer="1" position="6">
        <Product>None</Product>
        <Number>0</Number>
      </HeatPump>
      <HeatPump index="1" layer="1" position="7">
        <Product>None</Product>
        <Number>0</Number>
      </HeatPump>
      <HeatPump index="1" layer="1" position="8">
        <Product>None</Product>
        <Number>0</Number>
      </HeatPump>
    </HeatPumps>
    <Lamps>
      <Products>
        <Product Name="E HP Na 1000W">
          <Manufacture>NoName</Manufacture>
          <Name>E HP Na 1000W</Name>
          <LampType>HpSl</LampType>
          <Power>1035</Power>
          <MinPeriodOn>10</MinPeriodOn>
          <MicroMolParPerWattSeconds>1.787</MicroMolParPerWattSeconds>
          <Ballast>15</Ballast>
          <PropLw>0.1</PropLw>
          <PropSw>0.2</PropSw>
          <BallastPropLw>0.2</BallastPropLw>
          <LifeTime>12000</LifeTime>
        </Product>
        <Product Name="None">
          <Manufacture>None</Manufacture>
          <Name>None</Name>
          <LampType>Led</LampType>
          <Power>0</Power>
          <MinPeriodOn>10</MinPeriodOn>
          <MicroMolParPerWattSeconds>0</MicroMolParPerWattSeconds>
          <Ballast>0</Ballast>
          <PropLw>0</PropLw>
          <PropSw>0</PropSw>
          <BallastPropLw>0</BallastPropLw>
          <LifeTime>99000</LifeTime>
        </Product>
      </Products>
      <Lamp index="0" layer="0" position="1">
        <Product>E HP Na 1000W</Product>
        <Efficiency>1</Efficiency>
        <NumberInstalled>0.25</NumberInstalled>
        <Manufacture>NoName</Manufacture>
      </Lamp>
      <Lamp index="0" layer="0" position="2">
        <Product>None</Product>
        <Efficiency>1</Efficiency>
        <NumberInstalled>0.25</NumberInstalled>
        <Manufacture>None</Manufacture>
      </Lamp>
      <Lamp index="0" layer="0" position="3">
        <Product>None</Product>
        <Efficiency>1</Efficiency>
        <NumberInstalled>0.5</NumberInstalled>
        <Manufacture>None</Manufacture>
      </Lamp>
    </Lamps>
    <PadFans>
      <Products>
        <Product Name="None">
          <Efficiency>0</Efficiency>
          <MaxFlowRate>0</MaxFlowRate>
          <MaxParasitLoad>0</MaxParasitLoad>
        </Product>
      </Products>
      <PadFan index="1" layer="1" position="1">
        <Product>None</Product>
        <Number>0</Number>
      </PadFan>
      <PadFan index="1" layer="1" position="2">
        <Product>None</Product>
        <Number>0</Number>
      </PadFan>
      <PadFan index="1" layer="1" position="3">
        <Product>None</Product>
        <Number>0</Number>
      </PadFan>
      <PadFan index="1" layer="1" position="4">
        <Product>None</Product>
        <Number>0</Number>
      </PadFan>
      <PadFan index="1" layer="1" position="5">
        <Product>None</Product>
        <Number>0</Number>
      </PadFan>
      <PadFan index="1" layer="1" position="6">
        <Product>None</Product>
        <Number>0</Number>
      </PadFan>
      <PadFan index="1" layer="1" position="7">
        <Product>None</Product>
        <Number>0</Number>
      </PadFan>
      <PadFan index="1" layer="1" position="8">
        <Product>None</Product>
        <Number>0</Number>
      </PadFan>
    </PadFans>
    <Panes>
      <Products>
        <Product name="PC 3 wall 16 mm">  <!--NH-->
          <PaneTransmission>0.74</PaneTransmission>
          <PaneUValue>2.4</PaneUValue>
          <PaneReflection>0.26</PaneReflection>
          <PaneLwReflection>0.5</PaneLwReflection>
          <PaneLwTransmission>0.2</PaneLwTransmission>
          <PaneHeatCapacity>1</PaneHeatCapacity>
        </Product>
        <Product name="Single glass 4mm"> <!--NH-->
          <PaneTransmission>0.8</PaneTransmission>
          <PaneUValue>6.5</PaneUValue>
          <PaneReflection>0.1</PaneReflection>
          <PaneLwReflection>0.15</PaneLwReflection>
          <PaneLwTransmission>0.02</PaneLwTransmission>
          <PaneHeatCapacity>8400</PaneHeatCapacity>
        </Product>
      </Products>
      <Pane index="0" layer="0" position="1">
        <Product>Single glass 4mm</Product>
      </Pane>
      <Pane index="0" layer="0" position="2">
        <Product>Single glass 4mm</Product>
      </Pane>
      <Pane index="0" layer="0" position="3">
        <Product>PC 3 wall 16 mm</Product>
      </Pane>
      <Pane index="0" layer="0" position="4">
        <Product>PC 3 wall 16 mm</Product>
      </Pane>
      <Pane index="0" layer="0" position="5">
        <Product>PC 3 wall 16 mm</Product>
      </Pane>
      <Pane index="0" layer="0" position="6">
        <Product>PC 3 wall 16 mm</Product>
      </Pane>
      <Pane index="0" layer="0" position="7">
        <Product>Single glass 4mm</Product>
      </Pane>
      <Pane index="0" layer="0" position="8">
        <Product>Single glass 4mm</Product>
      </Pane>
    </Panes>
    <ScreenLayers>
      <ScreenLayer index="1" layer="1" position="0">
        <Actuator>Energy+Shade</Actuator>
      </ScreenLayer>
      <ScreenLayer index="2" layer="2" position="0">
        <Actuator>Shade</Actuator>
      </ScreenLayer>
      <ScreenLayer index="3" layer="3" position="0">
        <Actuator>Blackout</Actuator>
      </ScreenLayer>
    </ScreenLayers>
    <Screens>
      <!--Layer 1 er yderst, 2 dernæst og 3 inderst-->
      <Products>
        <Product name="LS Harmony 3647 FR"> <!--NH-->
          <Transmission>0.5</Transmission>
          <ReflectionOutwards>0.4</ReflectionOutwards>
          <ReflectionInwards>0.4</ReflectionInwards>
          <InsulationU>1.25</InsulationU>
          <U>0.6</U>
          <HeatCapacity>80</HeatCapacity>
          <EnergySaving>0.47</EnergySaving>
        </Product>
        <Product name="None"> <!--NH-->
          <Transmission>1</Transmission>
          <ReflectionOutwards>0</ReflectionOutwards>
          <ReflectionInwards>0</ReflectionInwards>
          <InsulationU>10</InsulationU>
          <U>0.6</U>
          <HeatCapacity>80</HeatCapacity>
          <EnergySaving>0</EnergySaving>
        </Product>
      </Products>
      <Screen index="1" layer="1" position="1">
        <Product>LS Harmony 3647 FR</Product>
        <Manufacture>LS</Manufacture>
      </Screen>
      <Screen index="2" layer="2" position="4">
        <Product>None</Product>
        <Manufacture>None</Manufacture>
      </Screen>
      <Screen index="2" layer="2" position="5">
        <Product>None</Product>
        <Manufacture>None</Manufacture>
      </Screen>
      <Screen index="2" layer="2" position="6">
        <Product>None</Product>
        <Manufacture>None</Manufacture>
      </Screen>
      <Screen index="3" layer="3" position="1">
        <Product>None</Product>
        <Manufacture>None</Manufacture>
      </Screen>
      <Screen index="3" layer="3" position="2">
        <Product>None</Product>
        <Manufacture>None</Manufacture>
      </Screen>
      <Screen index="3" layer="3" position="3">
        <Product>None</Product>
        <Manufacture>None</Manufacture>
      </Screen>
      <Screen index="3" layer="3" position="4">
        <Product>None</Product>
        <Manufacture>None</Manufacture>
      </Screen>
      <Screen index="3" layer="3" position="5">
        <Product>None</Product>
        <Manufacture>None</Manufacture>
      </Screen>
      <Screen index="3" layer="3" position="6">
        <Product>None</Product>
        <Manufacture>None</Manufacture>
      </Screen>
      <Screen index="1" layer="1" position="2">
        <Product>LS Harmony 3647 FR</Product>
        <Manufacture>LS</Manufacture>
      </Screen>
      <Screen index="1" layer="1" position="3">
        <Product>LS Harmony 3647 FR</Product>
        <Manufacture>LS</Manufacture>
      </Screen>
      <Screen index="1" layer="1" position="4">
        <Product>LS Harmony 3647 FR</Product>
        <Manufacture>LS</Manufacture>
      </Screen>
      <Screen index="1" layer="1" position="5">
        <Product>LS Harmony 3647 FR</Product>
        <Manufacture>LS</Manufacture>
      </Screen>
      <Screen index="1" layer="1" position="6">
        <Product>LS Harmony 3647 FR</Product>
        <Manufacture>LS</Manufacture>
      </Screen>
      <Screen index="2" layer="2" position="1">
        <Product>None</Product>
        <Manufacture>None</Manufacture>
      </Screen>
      <Screen index="2" layer="2" position="2">
        <Product>None</Product>
        <Manufacture>None</Manufacture>
      </Screen>
      <Screen index="2" layer="2" position="3">
        <Product>None</Product>
        <Manufacture>None</Manufacture>
      </Screen>
    </Screens>
    <Vents>
      <Vent index="0" layer="0" position="1">
        <Length>3</Length>
        <Width>3</Width>
        <Number>200</Number>
        <VentTransmissivity>1</VentTransmissivity>
      </Vent>
      <Vent index="0" layer="0" position="2">
        <Length>3</Length>
        <Width>3</Width>
        <Number>200</Number>
        <VentTransmissivity>1</VentTransmissivity>
        <MaxFlowRate>1</MaxFlowRate>
        <MaxCoolingLoad>1</MaxCoolingLoad>
        <CoolingEfficiency>1</CoolingEfficiency>
        <MaxParasitLoad>1</MaxParasitLoad>
        <CoolingTemperature>1</CoolingTemperature>
        <HeatRecovery>1</HeatRecovery>
      </Vent>
    </Vents>
    <ShadingAgents>
      <Products>
        <Product name="None"> <!--NH-->
          <SwReflectivity>0</SwReflectivity>
          <LwReflectivity>0</LwReflectivity>
        </Product>
      </Products>
      <ChosenProduct>None</ChosenProduct>
    </ShadingAgents>
  </Greenhouse>
  <Climate>
    <Setpoint>
      <HeatingTemp index="0" FromDate="01/01" FromTime="00:00" ToDate="31/12" ToTime="00:00">19</HeatingTemp>
      <HeatingTemp index="1" FromDate="01/01" FromTime="00:00" ToDate="31/12" ToTime="00:00">21</HeatingTemp>
      <VentTemp index="0" FromDate="01/01" FromTime="00:00" ToDate="31/12" ToTime="00:00">1</VentTemp>
      <VentTemp index="1" FromDate="01/01" FromTime="00:00" ToDate="31/12" ToTime="00:00">3</VentTemp>
      <Tavg index="0" FromDate="01/01" FromTime="00:00" ToDate="31/12" ToTime="00:00">21</Tavg>
      <TavgDays index="0" FromDate="01/01" FromTime="00:00" ToDate="31/12" ToTime="00:00">3</TavgDays>
      <TavgMax index="0" FromDate="01/01" FromTime="00:00" ToDate="31/12" ToTime="00:00">25</TavgMax>
      <TavgMin index="0" FromDate="01/01" FromTime="00:00" ToDate="31/12" ToTime="00:00">15</TavgMin>
      <TavgOn index="0" FromDate="01/01" FromTime="00:00" ToDate="31/12" ToTime="00:00">0</TavgOn>
      <heatPumpMaxPowerUse index="0" FromDate="01/01" FromTime="00:00" ToDate="31/12" ToTime="00:00">500</heatPumpMaxPowerUse>
      <heatPumpMode index="0" FromDate="01/01" FromTime="00:00" ToDate="31/12" ToTime="00:00">1 <!--NH-->
      <!--
        Da <Sp> indeholder default-værdien, skal de efterfølgende <Eq> elementer staret med "if"
        <Sp>0</Sp>
        <Eq>1</Eq>
        <Eq_vg>1</Eq_vg> -->
      </heatPumpMode>
      <HeatPumpTemp index="0" FromDate="01/01" FromTime="00:00" ToDate="31/12" ToTime="00:00">2</HeatPumpTemp>
      <crackVentilation index="0" FromDate="01/01" FromTime="00:00" ToDate="31/12" ToTime="00:00">0.05</crackVentilation>
      <crackVentilationTemperatureMin index="0" FromDate="01/01" FromTime="00:00" ToDate="31/12" ToTime="00:00">-5</crackVentilationTemperatureMin>
      <crackVentilationTemperatureMinBand index="0" FromDate="01/01" FromTime="00:00" ToDate="31/12" ToTime="00:00">1</crackVentilationTemperatureMinBand>
      <screenActive1 index="0" FromDate="01/01" FromTime="00:00" ToDate="31/12" ToTime="00:00">shade1+energy1</screenActive1>
      <screenActive1Layer index="0" FromDate="01/01" FromTime="00:00" ToDate="31/12" ToTime="00:00">missing</screenActive1Layer>
      <screenActive2 index="0" FromDate="01/01" FromTime="00:00" ToDate="31/12" ToTime="00:00">missing</screenActive2>
      <screenActive2Layer index="0" FromDate="01/01" FromTime="00:00" ToDate="31/12" ToTime="00:00">missing</screenActive2Layer>
      <screenActive3 index="0" FromDate="01/01" FromTime="00:00" ToDate="31/12" ToTime="00:00">missing</screenActive3>
      <screenActive3Layer index="0" FromDate="01/01" FromTime="00:00" ToDate="31/12" ToTime="00:00">missing</screenActive3Layer>
      <screenEnergyThreshold1 index="0" FromDate="01/01" FromTime="00:00" ToDate="31/12" ToTime="00:00">5</screenEnergyThreshold1>
      <screenEnergyThreshold2 index="0" FromDate="01/01" FromTime="00:00" ToDate="31/12" ToTime="00:00">5</screenEnergyThreshold2>
      <screenEnergyThresholdBand index="0" FromDate="01/01" FromTime="00:00" ToDate="31/12" ToTime="00:00">5</screenEnergyThresholdBand>
      <screenShadeThreshold1 index="0" FromDate="01/01" FromTime="00:00" ToDate="31/12" ToTime="00:00">500</screenShadeThreshold1>
      <screenShadeThreshold2 index="0" FromDate="01/01" FromTime="00:00" ToDate="31/12" ToTime="00:00">500</screenShadeThreshold2>
      <screenShadeThresholdBand index="0" FromDate="01/01" FromTime="00:00" ToDate="31/12" ToTime="00:00">50</screenShadeThresholdBand>
      <screenEnergyThreshold3 index="0" FromDate="01/01" FromTime="00:00" ToDate="31/12" ToTime="00:00">5</screenEnergyThreshold3>
      <screenFixed1 index="0" FromDate="01/01" FromTime="00:00" ToDate="31/12" ToTime="00:00">0</screenFixed1>
      <screenFixed2 index="0" FromDate="01/01" FromTime="00:00" ToDate="31/12" ToTime="00:00">0</screenFixed2>
      <screenFixed3 index="0" FromDate="01/01" FromTime="00:00" ToDate="31/12" ToTime="00:00">0</screenFixed3>
      <screenShadeThreshold3 index="0" FromDate="01/01" FromTime="00:00" ToDate="31/12" ToTime="00:00">500</screenShadeThreshold3>
      <ShadingAgentReduction index="0" FromDate="01/01" FromTime="00:00" ToDate="31/12" ToTime="00:00">0</ShadingAgentReduction>
      <AssLightActive1 index="0" FromDate="01/01" FromTime="00:00" ToDate="31/12" ToTime="00:00">1</AssLightActive1>
      <AssLightActive1 index="1" FromDate="01/01" FromTime="00:00" ToDate="31/12" ToTime="00:00">0</AssLightActive1>
      <AssLightActive2 index="0" FromDate="01/01" FromTime="00:00" ToDate="31/12" ToTime="00:00">0</AssLightActive2>
      <AssLightActive3 index="0" FromDate="01/01" FromTime="00:00" ToDate="31/12" ToTime="00:00">0</AssLightActive3>
      <AssLightOn1 index="0" FromDate="01/01" FromTime="00:00" ToDate="31/12" ToTime="00:00">5</AssLightOn1>
      <AssLightOff1 index="0" FromDate="01/01" FromTime="00:00" ToDate="31/12" ToTime="00:00">600</AssLightOff1>
      <AssLightOn2 index="0" FromDate="01/01" FromTime="00:00" ToDate="31/12" ToTime="00:00">5</AssLightOn2>
      <AssLightOff2 index="0" FromDate="01/01" FromTime="00:00" ToDate="31/12" ToTime="00:00">600</AssLightOff2>
      <AssLightOn3 index="0" FromDate="01/01" FromTime="00:00" ToDate="31/12" ToTime="00:00">5</AssLightOn3>
      <AssLightLightSum index="0" FromDate="01/01" FromTime="00:00" ToDate="31/12" ToTime="00:00">12</AssLightLightSum>
      <AssLightLightSumDays index="0" FromDate="01/01" FromTime="00:00" ToDate="31/12" ToTime="00:00">3</AssLightLightSumDays>
      <AssLightOff3 index="0" FromDate="01/01" FromTime="00:00" ToDate="31/12" ToTime="00:00">600</AssLightOff3>
      <MaxRelHmd index="0" FromDate="01/01" FromTime="00:00" ToDate="31/12" ToTime="00:00">85</MaxRelHmd>
      <MaxHeatAddHighRH index="0" FromDate="01/01" FromTime="00:00" ToDate="31/12" ToTime="00:00">2</MaxHeatAddHighRH>
      <rhMaxBand index="0" FromDate="01/01" FromTime="00:00" ToDate="31/12" ToTime="00:00">5</rhMaxBand>
      <minPipeTemperature index="0" FromDate="01/01" FromTime="00:00" ToDate="31/12" ToTime="00:00">20</minPipeTemperature>
      <maxPipeTemperature index="0" FromDate="01/01" FromTime="00:00" ToDate="31/12" ToTime="00:00">95</maxPipeTemperature>
      <FogActive index="0" FromDate="01/01" FromTime="00:00" ToDate="31/12" ToTime="00:00">missing</FogActive>
      <CO2Setpoint index="0" FromDate="01/01" FromTime="00:00" ToDate="31/12" ToTime="00:00">900</CO2Setpoint>
      <CO2Capacity index="0" FromDate="01/01" FromTime="00:00" ToDate="31/12" ToTime="00:00">50</CO2Capacity>
      <CO2VentilationBand index="0" FromDate="01/01" FromTime="00:00" ToDate="31/12" ToTime="00:00">0.2</CO2VentilationBand>
      <CO2VentilationThreshold index="0" FromDate="01/01" FromTime="00:00" ToDate="31/12" ToTime="00:00">0.1</CO2VentilationThreshold>
    </Setpoint>
  </Climate>
  <Output>
    <Period>10</Period>
    <UseLocalDecimalChar>0</UseLocalDecimalChar>
    <SkipFormats>0</SkipFormats>
    <Variables>
      <!--NH attributen 'name' skal skrives med småt (ikke 'Name')-->
      <Variable name="actCo2" path="actuators/co2[value]" />
      <Variable name="actHeatingPower" path="actuators/heatPipes[heatFlux]" />
      <Variable name="actLight1" path="actuators/growthLights/bank1[powerUsage]" />
      <Variable name="actLight2" path="actuators/growthLights/bank2[powerUsage]" />
      <Variable name="actLight3" path="actuators/growthLights/bank3[powerUsage]" />
      <Variable name="actLightPar" path="actuators/growthLights[parEmissionBottom]" />
      <Variable name="actLightPower" path="actuators/growthLights[powerUsage]" />
      <Variable name="actPipeTempIn1" path="actuators/heatPipes/circuit1[inflowTemperature]" />
      <Variable name="actPipeTempIn2" path="actuators/heatPipes/circuit2[inflowTemperature]" />
      <Variable name="actPipeTempOut1" path="actuators/heatPipes/circuit1[outflowTemperature]" />
      <Variable name="actPipeTempOut2" path="actuators/heatPipes/circuit2[outflowTemperature]" />
      <Variable name="actScreen1 " path="actuators/screens/layer1[state]" />
      <Variable name="actScreen2" path="actuators/screens/layer2[state]" />
      <Variable name="actScreen3" path="actuators/screens/layer3[state]" />
      <Variable name="actVentilation" path="actuators/ventilation[ventFlux]" />
      <Variable name="airFluxTotal" path="actuators/ventilation[value]" />
      <Variable name="balanceConv" path="budget/cover[convectionTop]" />
      <Variable name="balanceLw" path="budget/cover[lwAbsorbedTop] - budget/cover[lwEmissionTop]" />
      <Variable name="balanceVent" path="budget[ventilationHeatLoss]" />
      <Variable name="condensationCover" path="budget[condensationCover]" />
      <Variable name="condensationHeatPump" path="budget[condensationHeatPump]" />
      <Variable name="coverT" path="budget/cover[temperature]" />
      <Variable name="floorT" path="budget/floor[temperature]" />
      <Variable name="fogPowerUse" path="actuators/humidifiers/powerUse[value]" />
      <Variable name="fogState" path="controllers/humidification[state]" />
      <Variable name="fogVapourFlux" path="actuators/humidifiers/vapourFlux[value]" />
      <Variable name="grossAssimilationRate" path="plant[Pg]" />
      <Variable name="heatBufferOutput" path="heatBuffer[outputSupply]" />
      <Variable name="heatBufferTemp" path="heatBuffer[temperature]" />
      <Variable name="heatFluxCover" path="budget/cover[convectionTop]" />
      <Variable name="heatFluxFloor" path="budget/cover[convectionBottom]" />
      <Variable name="heatPumpCondensation" path="actuators/heatPumps/condensation[value]" /> <!--NH-->
      <Variable name="heatPumpCooling " path="actuators/heatPumps/cooling[value]" />
      <Variable name="heatPumpPowerUse" path="actuators/heatPumps/powerUse[value]" />
      <Variable name="heatPumpState" path="controllers/heatPumps/state[value]" />
      <Variable name="indoorsCo2" path="budget/indoors[co2]" />
      <Variable name="indoorsGrowthLightPar" path="actuators/growthLights[parEmissionBottom]" />
      <Variable name="indoorsRh" path="budget/indoors[rh]" />
      <Variable name="indoorsT" path="budget/indoors[temperature]" />
      <Variable name="indoorsTavg" path="indoorsTemperature[average]" />
      <Variable name="indoorsTotalPar" path="plant[incidentPar]" />
      <Variable name="leafT" path="budget/plant[temperature]" />
      <Variable name="lightSum" path="lightSum[value]" />
      <Variable name="lightUseEfficiency" path="plant[lue]" />
      <Variable name="lwAbsorbedCover" path="budget/cover[lwAbsorbedTop]" />
      <Variable name="lwEmissionCover" path="budget/cover[lwEmissionTop]" />
      <Variable name="netAssimilationRate" path="plant[Pn]" />
      <Variable name="netGrowthRate" path="plant[growthRate]" />
      <Variable name="netGrowthRateLeaf" path="plant[leafGrowthRate]" />
      <Variable name="outdoorsLight" path="outdoors[radiation]" />
      <Variable name="outdoorsPar" path="outdoors[par]" />
      <Variable name="outdoorsRh" path="outdoors[rh]" />
      <Variable name="outdoorsT" path="outdoors[temperature]" />
      <Variable name="outdoorsWindSpeed" path="outdoors[windSpeed]" />
      <Variable name="pipeT" path="budget/heatPipes[temperature]" />
      <Variable name="respirationRate" path="plant[Rd]" />
      <Variable name="screen1T" path="budget/screen1[temperature]" />
      <Variable name="screen2T" path="budget/screen2[temperature]" />
      <Variable name="screen3T" path="budget/screen3[temperature]" />
      <Variable name="sensibleVentFlux" path="budget[ventilationHeatLoss]" />
      <Variable name="skyT" path="budget/sky[temperature]" />
      <Variable name="soilT" path="outdoors[soilTemperature]" />
      <Variable name="spCo2" path="setpoints/co2/concentration[value]" />
      <Variable name="spHeatingTemperature" path="controllers/desiredMinTemperature[value]" />
      <Variable name="spHeatPumpTemperature" path="controllers/heatPumps/desiredMaxTemperature[value]" />
      <Variable name="spVentilationTemperature" path="controllers/ventilation/desiredMaxTemperature[value]" />
      <Variable name="transpiration" path="plant[transpiration]" />
      <Variable name="Uinside" path="shelter/layers/cover[UbottomAdj]" />
      <Variable name="Uoutside" path="shelter/layers/cover[UtopAdj]" />
      <Variable name="ventedWater" path="budget[ventedWater]" />
      <Variable name="ventOpening" path="actuators/ventilation[opening]" />
    </Variables>
  </Output>
  <Status>
    <LigthSum>
      <Period>10</Period>
    </LigthSum>
    <TwemperatureAvg>
      <Period>20</Period>
    </TwemperatureAvg>
  </Status>
</VG_SETUP>